PyLogAnim/__init__.py
PyLogAnim/__main__.py
PyLogAnim/colormodes.py
PyLogAnim/demo_logos.py
PyLogAnim/termcheck.py
PyLogAnim-27032025.dist-info/METADATA
PyLogAnim-27032025.dist-info/WHEEL
PyLogAnim-27032025.dist-info/top_level.txt
PyLogAnim-27032025.dist-info/RECORD
