Metadata-Version: 2.2
Name: PyLogAnim
Version: 27032025
Summary: A library for animating your logos
Home-page: https://github.com/lz-fkn/PyLogAnim
Author: Elzzie
Author-email: fractus.lol@proton.me
Requires-Dist: colorama
Dynamic: author
Dynamic: author-email
Dynamic: description
Dynamic: description-content-type
Dynamic: home-page
Dynamic: requires-dist
Dynamic: summary
